pdf_box_fields/__init__.py
pdf_box_fields/cli.py
pdf_box_fields/config.py
pdf_box_fields/extract.py
pdf_box_fields/io_utils.py
pdf_box_fields/layout.py
pdf_box_fields/main.py
pdf_box_fields/markup_and_fields.py
pdf_box_fields/utils.py
pdf_box_fields-2025.8.29.dist-info/licenses/LICENSE
tests/__init__.py
tests/test_extract.py
tests/test_io_utils.py
tests/test_layout.py
tests/test_main.py
tests/test_markup_and_fields.py
tests/test_utils.py
pdf_box_fields-2025.8.29.dist-info/METADATA
pdf_box_fields-2025.8.29.dist-info/WHEEL
pdf_box_fields-2025.8.29.dist-info/entry_points.txt
pdf_box_fields-2025.8.29.dist-info/top_level.txt
pdf_box_fields-2025.8.29.dist-info/RECORD
