Metadata-Version: 2.4
Name: pdf-box-fields
Version: 2025.8.29
Summary: Tools for extracting, processing, and generating interactive fields for PDFs containing white box fields.
Author-email: flywire <flywire0@gmail.com>
License: GPL-3.0-or-later
Keywords: pdf,form,fields,extraction,pymupdf,pypdfforms
Classifier: Development Status :: 4 - Beta
Classifier: Intended Audience :: Developers
Classifier: License :: OSI Approved :: GNU General Public License v3 or later (GPLv3+)
Classifier: Programming Language :: Python :: 3
Classifier: Programming Language :: Python :: 3.8
Classifier: Programming Language :: Python :: 3.9
Classifier: Programming Language :: Python :: 3.10
Classifier: Topic :: Software Development :: Libraries
Requires-Python: >=3.8
License-File: LICENSE
Requires-Dist: PyMuPDF>=1.18.0
Requires-Dist: PyPDFForm>=0.3.3
Dynamic: license-file
